pytorch_model_wrapper/__init__.py
pytorch_model_wrapper/fittable_model_wrapper.py
pytorch_model_wrapper/fittable_model_wrapper_commons.py
pytorch_model_wrapper/fittable_model_wrapper_utils.py
pytorch_model_wrapper-0.0.4.dist-info/LICENSE
pytorch_model_wrapper-0.0.4.dist-info/METADATA
pytorch_model_wrapper-0.0.4.dist-info/WHEEL
pytorch_model_wrapper-0.0.4.dist-info/top_level.txt
pytorch_model_wrapper-0.0.4.dist-info/RECORD
