Metadata-Version: 2.1
Name: pytorch-model-wrapper
Version: 0.0.4
Summary: Pytorch model wrapper
Author: Mikhail Gubarenko
Author-email: dmdgik@gmail.com
License: Apache-2.0
Classifier: Intended Audience :: Developers
Classifier: License :: OSI Approved :: Apache Software License
Classifier: Programming Language :: Python :: 3
Classifier: Programming Language :: Python :: 3.8
Classifier: Programming Language :: Python :: 3.9
Classifier: Operating System :: OS Independent
License-File: LICENSE
Requires-Dist: tqdm
Requires-Dist: torch
Requires-Dist: accelerate
Requires-Dist: mlflow
Requires-Dist: loguru
Requires-Dist: pyyaml
Requires-Dist: boto3
Requires-Dist: tensorboard
